fewshotlib/__init__.py
fewshotlib/fewshotlib.py
fewshotlib-0.1.1.dist-info/licenses/LICENSE.txt
fewshotlib-0.1.1.dist-info/METADATA
fewshotlib-0.1.1.dist-info/WHEEL
fewshotlib-0.1.1.dist-info/top_level.txt
fewshotlib-0.1.1.dist-info/RECORD
