Metadata-Version: 2.4
Name: fewshotlib
Version: 0.1.1
Summary: A flexible few-shot classifier toolkit.
Author: Rohit Gomes
Author-email: gomesrohit92@gmail.com
Requires-Python: >=3.8
License-File: LICENSE.txt
Requires-Dist: torch>=1.10.0
Requires-Dist: torchvision>=0.11.0
Requires-Dist: Pillow
Dynamic: author
Dynamic: author-email
Dynamic: description
Dynamic: description-content-type
Dynamic: license-file
Dynamic: requires-dist
Dynamic: requires-python
Dynamic: summary
